{"cameraMode":{"drawMode":0,"name":"Shaded","section":"Shading Mode"},"sceneLighting":true,"audioPlay":false,"sceneViewState":{"showFog":true,"showMaterialUpdate":false,"showSkybox":true,"showFlares":true,"showImageEffects":true,"showParticleSystems":true},"in2DMode":false,"pivot":{"x":469.9170227050781,"y":236.28024291992188,"z":-115.61883544921875},"rotation":{"x":-2.2298409874110804e-7,"y":-0.04738029092550278,"z":0.0000042993187889805998,"w":0.9988895654678345},"size":314.0783996582031,"orthographic":false}